econagents_ibex_tudelft/__init__.py
econagents_ibex_tudelft/config_parser/__init__.py
econagents_ibex_tudelft/config_parser/ibex_tudelft.py
econagents_ibex_tudelft/core/__init__.py
econagents_ibex_tudelft/core/state/__init__.py
econagents_ibex_tudelft/core/state/chat.py
econagents_ibex_tudelft/core/state/market.py
econagents_ibex_tudelft-0.0.2.dist-info/LICENSE
econagents_ibex_tudelft-0.0.2.dist-info/METADATA
econagents_ibex_tudelft-0.0.2.dist-info/WHEEL
econagents_ibex_tudelft-0.0.2.dist-info/RECORD
