Metadata-Version: 2.3
Name: econagents-ibex-tudelft
Version: 0.0.2
Summary: 
License: MIT
Author: Dylan Castillo
Author-email: dylan@iwanalabs.com
Requires-Python: >=3.10,<4
Classifier: License :: OSI Approved :: MIT License
Classifier: Programming Language :: Python :: 3
Classifier: Programming Language :: Python :: 3.10
Classifier: Programming Language :: Python :: 3.11
Classifier: Programming Language :: Python :: 3.12
Classifier: Programming Language :: Python :: 3.13
Requires-Dist: econagents[all] (>=0.0.0)
